bigotis/__init__.py
bigotis/modeling_utils.py
bigotis/models/__init__.py
bigotis/models/aphantasia/__init__.py
bigotis/models/aphantasia/modeling_aphantasia.py
bigotis/models/dalle_mini/__init__.py
bigotis/models/dalle_mini/modeling_dalle_mini.py
bigotis/models/taming/__init__.py
bigotis/models/taming/modeling_taming.py
forks/__init__.py
forks/dalle_mini/__init__.py
forks/dalle_mini/dalle_mini/__init__.py
forks/dalle_mini/dalle_mini/backend.py
forks/dalle_mini/dalle_mini/dataset.py
forks/dalle_mini/dalle_mini/helpers.py
forks/dalle_mini/dalle_mini/model.py
forks/taming_transformers/__init__.py
forks/taming_transformers/main.py
forks/taming_transformers/setup.py
forks/taming_transformers/taming/__init__.py
forks/taming_transformers/taming/lr_scheduler.py
forks/taming_transformers/taming/util.py
forks/taming_transformers/taming/data/__init__.py
forks/taming_transformers/taming/data/ade20k.py
forks/taming_transformers/taming/data/annotated_objects_coco.py
forks/taming_transformers/taming/data/annotated_objects_dataset.py
forks/taming_transformers/taming/data/base.py
forks/taming_transformers/taming/data/coco.py
forks/taming_transformers/taming/data/custom.py
forks/taming_transformers/taming/data/faceshq.py
forks/taming_transformers/taming/data/helper_types.py
forks/taming_transformers/taming/data/image_transforms.py
forks/taming_transformers/taming/data/imagenet.py
forks/taming_transformers/taming/data/sflckr.py
forks/taming_transformers/taming/data/utils.py
forks/taming_transformers/taming/data/conditional_builder/__init__.py
forks/taming_transformers/taming/data/conditional_builder/objects_bbox.py
forks/taming_transformers/taming/data/conditional_builder/objects_center_points.py
forks/taming_transformers/taming/data/conditional_builder/utils.py
forks/taming_transformers/taming/models/__init__.py
forks/taming_transformers/taming/models/cond_transformer.py
forks/taming_transformers/taming/models/dummy_cond_stage.py
forks/taming_transformers/taming/models/vqgan.py
hugging_gan_test-0.2.29.dist-info/LICENSE
hugging_gan_test-0.2.29.dist-info/METADATA
hugging_gan_test-0.2.29.dist-info/WHEEL
hugging_gan_test-0.2.29.dist-info/top_level.txt
hugging_gan_test-0.2.29.dist-info/RECORD
