Metadata-Version: 2.1
Name: hugging-gan-test
Version: 0.2.29
Summary: Testing pip
Home-page: https://github.com/javismiles/HuggingGAN
Author: Javi and Vicc
Author-email: vipermu97@gmail.com
License: UNKNOWN
Project-URL: Docs, https://github.com/javismiles/HuggingGAN/docs
Platform: UNKNOWN
Classifier: Programming Language :: Python :: 3
Classifier: License :: OSI Approved :: MIT License
Classifier: Operating System :: OS Independent
Requires-Python: >=3.6
License-File: LICENSE
Requires-Dist: tqdm (==4.60.0)
Requires-Dist: clip-by-openai
Requires-Dist: dall-e (==0.1)
Requires-Dist: imageio-ffmpeg (==0.4.3)
Requires-Dist: PyYAML (==5.4.1)
Requires-Dist: omegaconf (==2.0.6)
Requires-Dist: pytorch-lightning (==1.3.3)
Requires-Dist: einops (==0.3.0)
Requires-Dist: imageio (==2.9.0)
Requires-Dist: torch (==1.7.1)
Requires-Dist: torchvision (==0.8.2)
Requires-Dist: tensorboard (>=2.2.0)
Requires-Dist: transformers (>=4.10.0)
Requires-Dist: flax (>=0.3.4)
Requires-Dist: jax
Requires-Dist: kornia
